{".class":"MypyFile","_fullname":"locust.dispatch","future_import_flags":["annotations"],"is_partial_stub_package":false,"is_stub":false,"names":{".class":"SymbolTable","Generator":{".class":"SymbolTableNode","cross_ref":"typing.Generator","kind":"Gdef"},"Iterable":{".class":"SymbolTableNode","cross_ref":"typing.Iterable","kind":"Gdef"},"Iterator":{".class":"SymbolTableNode","cross_ref":"typing.Iterator","kind":"Gdef"},"T":{".class":"SymbolTableNode","kind":"Gdef","node":{".class":"TypeVarExpr","default":{".class":"AnyType","missing_import_name":null,"source_any":null,"type_of_any":4},"fullname":"locust.dispatch.T","name":"T","upper_bound":"builtins.object","values":[],"variance":0}},"TYPE_CHECKING":{".class":"SymbolTableNode","cross_ref":"typing.TYPE_CHECKING","kind":"Gdef"},"TypeVar":{".class":"SymbolTableNode","cross_ref":"typing.TypeVar","kind":"Gdef"},"User":{".class":"SymbolTableNode","cross_ref":"locust.user.users.User","kind":"Gdef"},"UsersDispatcher":{".class":"SymbolTableNode","kind":"Gdef","node":{".class":"TypeInfo","_promote":[],"abstract_attributes":[],"alt_promote":null,"bases":[{".class":"Instance","args":[{".class":"AnyType","missing_import_name":null,"source_any":null,"type_of_any":4}],"extra_attrs":null,"type_ref":"typing.Iterator"}],"dataclass_transform_spec":null,"declared_metaclass":null,"defn":{".class":"ClassDef","fullname":"locust.dispatch.UsersDispatcher","name":"UsersDispatcher","type_vars":[]},"deletable_attributes":[],"deprecated":null,"flags":[],"fullname":"locust.dispatch.UsersDispatcher","has_param_spec_type":false,"metaclass_type":"abc.ABCMeta","metadata":{},"module_name":"locust.dispatch","mro":["locust.dispatch.UsersDispatcher","typing.Iterator","typing.Iterable","builtins.object"],"names":{".class":"SymbolTable","__init__":{".class":"SymbolTableNode","kind":"Mdef","node":{".class":"FuncDef","abstract_status":0,"arg_kinds":[0,0,0],"arg_names":["self","worker_nodes","user_classes"],"dataclass_transform_spec":null,"deprecated":null,"flags":["is_trivial_self"],"fullname":"locust.dispatch.UsersDispatcher.__init__","name":"__init__","original_first_arg":"self","type":{".class":"CallableType","arg_kinds":[0,0,0],"arg_names":["self","worker_nodes","user_classes"],"arg_types":["locust.dispatch.UsersDispatcher",{".class":"Instance","args":["locust.runners.WorkerNode"],"extra_attrs":null,"type_ref":"builtins.list"},{".class":"Instance","args":[{".class":"TypeType","is_type_form":false,"item":"locust.user.users.User"}],"extra_attrs":null,"type_ref":"builtins.list"}],"fallback":"builtins.function","from_concatenate":false,"implicit":false,"imprecise_arg_kinds":false,"is_bound":false,"is_ellipsis_args":false,"name":"__init__ of UsersDispatcher","ret_type":{".class":"NoneType"},"type_guard":null,"type_is":null,"unpack_kwargs":false,"variables":[]}}},"__next__":{".class":"SymbolTableNode","kind":"Mdef","node":{".class":"FuncDef","abstract_status":0,"arg_kinds":[0],"arg_names":["self"],"dataclass_transform_spec":null,"deprecated":null,"flags":["is_trivial_self"],"fullname":"locust.dispatch.UsersDispatcher.__next__","name":"__next__","original_first_arg":"self","type":{".class":"CallableType","arg_kinds":[0],"arg_names":["self"],"arg_types":["locust.dispatch.UsersDispatcher"],"fallback":"builtins.function","from_concatenate":false,"implicit":false,"imprecise_arg_kinds":false,"is_bound":false,"is_ellipsis_args":false,"name":"__next__ of UsersDispatcher","ret_type":{".class":"Instance","args":["builtins.str",{".class":"Instance","args":["builtins.str","builtins.int"],"extra_attrs":null,"type_ref":"builtins.dict"}],"extra_attrs":null,"type_ref":"builtins.dict"},"type_guard":null,"type_is":null,"unpack_kwargs":false,"variables":[]}}},"_active_users":{".class":"SymbolTableNode","implicit":true,"kind":"Mdef","node":{".class":"Var","flags":["explicit_self_type","is_ready","is_inferred"],"fullname":"locust.dispatch.UsersDispatcher._active_users","name":"_active_users","setter_type":null,"type":{".class":"Instance","args":[{".class":"TupleType","implicit":false,"items":["locust.runners.WorkerNode","builtins.str"],"partial_fallback":{".class":"Instance","args":[{".class":"AnyType","missing_import_name":null,"source_any":null,"type_of_any":6}],"extra_attrs":null,"type_ref":"builtins.tuple"}}],"extra_attrs":null,"type_ref":"builtins.list"}}},"_add_users_on_workers":{".class":"SymbolTableNode","kind":"Mdef","node":{".class":"FuncDef","abstract_status":0,"arg_kinds":[0],"arg_names":["self"],"dataclass_transform_spec":null,"deprecated":null,"flags":["is_trivial_self"],"fullname":"locust.dispatch.UsersDispatcher._add_users_on_workers","name":"_add_users_on_workers","original_first_arg":"self","type":{".class":"CallableType","arg_kinds":[0],"arg_names":["self"],"arg_types":["locust.dispatch.UsersDispatcher"],"fallback":"builtins.function","from_concatenate":false,"implicit":false,"imprecise_arg_kinds":false,"is_bound":false,"is_ellipsis_args":false,"name":"_add_users_on_workers of UsersDispatcher","ret_type":{".class":"Instance","args":["builtins.str",{".class":"Instance","args":["builtins.str","builtins.int"],"extra_attrs":null,"type_ref":"builtins.dict"}],"extra_attrs":null,"type_ref":"builtins.dict"},"type_guard":null,"type_is":null,"unpack_kwargs":false,"variables":[]}}},"_current_user_count":{".class":"SymbolTableNode","implicit":true,"kind":"Mdef","node":{".class":"Var","flags":["is_ready","is_inferred"],"fullname":"locust.dispatch.UsersDispatcher._current_user_count","name":"_current_user_count","setter_type":null,"type":"builtins.int"}},"_dispatch_in_progress":{".class":"SymbolTableNode","implicit":true,"kind":"Mdef","node":{".class":"Var","flags":["is_ready","is_inferred"],"fullname":"locust.dispatch.UsersDispatcher._dispatch_in_progress","name":"_dispatch_in_progress","setter_type":null,"type":"builtins.bool"}},"_dispatch_iteration_durations":{".class":"SymbolTableNode","implicit":true,"kind":"Mdef","node":{".class":"Var","flags":["explicit_self_type","is_ready","is_inferred"],"fullname":"locust.dispatch.UsersDispatcher._dispatch_iteration_durations","name":"_dispatch_iteration_durations","setter_type":null,"type":{".class":"Instance","args":["builtins.float"],"extra_attrs":null,"type_ref":"builtins.list"}}},"_dispatcher":{".class":"SymbolTableNode","kind":"Mdef","node":{".class":"FuncDef","abstract_status":0,"arg_kinds":[0],"arg_names":["self"],"dataclass_transform_spec":null,"deprecated":null,"flags":["is_generator","is_trivial_self"],"fullname":"locust.dispatch.UsersDispatcher._dispatcher","name":"_dispatcher","original_first_arg":"self","type":{".class":"CallableType","arg_kinds":[0],"arg_names":["self"],"arg_types":["locust.dispatch.UsersDispatcher"],"fallback":"builtins.function","from_concatenate":false,"implicit":false,"imprecise_arg_kinds":false,"is_bound":false,"is_ellipsis_args":false,"name":"_dispatcher of UsersDispatcher","ret_type":{".class":"Instance","args":[{".class":"Instance","args":["builtins.str",{".class":"Instance","args":["builtins.str","builtins.int"],"extra_attrs":null,"type_ref":"builtins.dict"}],"extra_attrs":null,"type_ref":"builtins.dict"},{".class":"NoneType"},{".class":"NoneType"}],"extra_attrs":null,"type_ref":"typing.Generator"},"type_guard":null,"type_is":null,"unpack_kwargs":false,"variables":[]}}},"_dispatcher_generator":{".class":"SymbolTableNode","implicit":true,"kind":"Mdef","node":{".class":"Var","flags":["explicit_self_type","is_ready","is_inferred"],"fullname":"locust.dispatch.UsersDispatcher._dispatcher_generator","name":"_dispatcher_generator","setter_type":null,"type":{".class":"Instance","args":[{".class":"Instance","args":["builtins.str",{".class":"Instance","args":["builtins.str","builtins.int"],"extra_attrs":null,"type_ref":"builtins.dict"}],"extra_attrs":null,"type_ref":"builtins.dict"},{".class":"NoneType"},{".class":"NoneType"}],"extra_attrs":null,"type_ref":"typing.Generator"}}},"_distribute_users":{".class":"SymbolTableNode","kind":"Mdef","node":{".class":"FuncDef","abstract_status":0,"arg_kinds":[0,0],"arg_names":["self","target_user_count"],"dataclass_transform_spec":null,"deprecated":null,"flags":["is_trivial_self"],"fullname":"locust.dispatch.UsersDispatcher._distribute_users","name":"_distribute_users","original_first_arg":"self","type":{".class":"CallableType","arg_kinds":[0,0],"arg_names":["self","target_user_count"],"arg_types":["locust.dispatch.UsersDispatcher","builtins.int"],"fallback":"builtins.function","from_concatenate":false,"implicit":false,"imprecise_arg_kinds":false,"is_bound":false,"is_ellipsis_args":false,"name":"_distribute_users of UsersDispatcher","ret_type":{".class":"TupleType","implicit":false,"items":[{".class":"Instance","args":["builtins.str",{".class":"Instance","args":["builtins.str","builtins.int"],"extra_attrs":null,"type_ref":"builtins.dict"}],"extra_attrs":null,"type_ref":"builtins.dict"},{".class":"Instance","args":[{".class":"UnionType","items":["builtins.str",{".class":"NoneType"}],"uses_pep604_syntax":true}],"extra_attrs":null,"type_ref":"typing.Iterator"},{".class":"Instance","args":[{".class":"AnyType","missing_import_name":null,"source_any":null,"type_of_any":4}],"extra_attrs":null,"type_ref":"itertools.cycle"},{".class":"Instance","args":[{".class":"TupleType","implicit":false,"items":["locust.runners.WorkerNode","builtins.str"],"partial_fallback":{".class":"Instance","args":[{".class":"AnyType","missing_import_name":null,"source_any":null,"type_of_any":6}],"extra_attrs":null,"type_ref":"builtins.tuple"}}],"extra_attrs":null,"type_ref":"builtins.list"}],"partial_fallback":{".class":"Instance","args":[{".class":"AnyType","missing_import_name":null,"source_any":null,"type_of_any":6}],"extra_attrs":null,"type_ref":"builtins.tuple"}},"type_guard":null,"type_is":null,"unpack_kwargs":false,"variables":[]}}},"_fast_users_on_workers_copy":{".class":"SymbolTableNode","kind":"Mdef","node":{".class":"Decorator","func":{".class":"FuncDef","abstract_status":0,"arg_kinds":[0],"arg_names":["users_on_workers"],"dataclass_transform_spec":null,"deprecated":null,"flags":["is_static","is_decorated"],"fullname":"locust.dispatch.UsersDispatcher._fast_users_on_workers_copy","name":"_fast_users_on_workers_copy","original_first_arg":"users_on_workers","type":{".class":"CallableType","arg_kinds":[0],"arg_names":["users_on_workers"],"arg_types":[{".class":"Instance","args":["builtins.str",{".class":"Instance","args":["builtins.str","builtins.int"],"extra_attrs":null,"type_ref":"builtins.dict"}],"extra_attrs":null,"type_ref":"builtins.dict"}],"fallback":"builtins.function","from_concatenate":false,"implicit":false,"imprecise_arg_kinds":false,"is_bound":false,"is_ellipsis_args":false,"name":"_fast_users_on_workers_copy of UsersDispatcher","ret_type":{".class":"Instance","args":["builtins.str",{".class":"Instance","args":["builtins.str","builtins.int"],"extra_attrs":null,"type_ref":"builtins.dict"}],"extra_attrs":null,"type_ref":"builtins.dict"},"type_guard":null,"type_is":null,"unpack_kwargs":false,"variables":[]}},"is_overload":false,"var":{".class":"Var","flags":["is_initialized_in_class","is_staticmethod","is_ready","is_inferred"],"fullname":"locust.dispatch.UsersDispatcher._fast_users_on_workers_copy","name":"_fast_users_on_workers_copy","setter_type":null,"type":{".class":"CallableType","arg_kinds":[0],"arg_names":["users_on_workers"],"arg_types":[{".class":"Instance","args":["builtins.str",{".class":"Instance","args":["builtins.str","builtins.int"],"extra_attrs":null,"type_ref":"builtins.dict"}],"extra_attrs":null,"type_ref":"builtins.dict"}],"fallback":"builtins.function","from_concatenate":false,"implicit":false,"imprecise_arg_kinds":false,"is_bound":false,"is_ellipsis_args":false,"name":"_fast_users_on_workers_copy of UsersDispatcher","ret_type":{".class":"Instance","args":["builtins.str",{".class":"Instance","args":["builtins.str","builtins.int"],"extra_attrs":null,"type_ref":"builtins.dict"}],"extra_attrs":null,"type_ref":"builtins.dict"},"type_guard":null,"type_is":null,"unpack_kwargs":false,"variables":[]}}}},"_get_user_current_count":{".class":"SymbolTableNode","kind":"Mdef","node":{".class":"FuncDef","abstract_status":0,"arg_kinds":[0,0],"arg_names":["self","user"],"dataclass_transform_spec":null,"deprecated":null,"flags":["is_trivial_self"],"fullname":"locust.dispatch.UsersDispatcher._get_user_current_count","name":"_get_user_current_count","original_first_arg":"self","type":{".class":"CallableType","arg_kinds":[0,0],"arg_names":["self","user"],"arg_types":["locust.dispatch.UsersDispatcher","builtins.str"],"fallback":"builtins.function","from_concatenate":false,"implicit":false,"imprecise_arg_kinds":false,"is_bound":false,"is_ellipsis_args":false,"name":"_get_user_current_count of UsersDispatcher","ret_type":"builtins.int","type_guard":null,"type_is":null,"unpack_kwargs":false,"variables":[]}}},"_initial_users_on_workers":{".class":"SymbolTableNode","implicit":true,"kind":"Mdef","node":{".class":"Var","flags":["is_ready","is_inferred"],"fullname":"locust.dispatch.UsersDispatcher._initial_users_on_workers","name":"_initial_users_on_workers","setter_type":null,"type":{".class":"Instance","args":["builtins.str",{".class":"Instance","args":["builtins.str","builtins.int"],"extra_attrs":null,"type_ref":"builtins.dict"}],"extra_attrs":null,"type_ref":"builtins.dict"}}},"_no_user_to_spawn":{".class":"SymbolTableNode","implicit":true,"kind":"Mdef","node":{".class":"Var","flags":["is_ready","is_inferred"],"fullname":"locust.dispatch.UsersDispatcher._no_user_to_spawn","name":"_no_user_to_spawn","setter_type":null,"type":"builtins.bool"}},"_original_user_classes":{".class":"SymbolTableNode","implicit":true,"kind":"Mdef","node":{".class":"Var","flags":["is_ready","is_inferred"],"fullname":"locust.dispatch.UsersDispatcher._original_user_classes","name":"_original_user_classes","setter_type":null,"type":{".class":"Instance","args":[{".class":"TypeType","is_type_form":false,"item":"locust.user.users.User"}],"extra_attrs":null,"type_ref":"builtins.list"}}},"_prepare_rebalance":{".class":"SymbolTableNode","kind":"Mdef","node":{".class":"FuncDef","abstract_status":0,"arg_kinds":[0],"arg_names":["self"],"dataclass_transform_spec":null,"deprecated":null,"flags":["is_trivial_self"],"fullname":"locust.dispatch.UsersDispatcher._prepare_rebalance","name":"_prepare_rebalance","original_first_arg":"self","type":{".class":"CallableType","arg_kinds":[0],"arg_names":["self"],"arg_types":["locust.dispatch.UsersDispatcher"],"fallback":"builtins.function","from_concatenate":false,"implicit":false,"imprecise_arg_kinds":false,"is_bound":false,"is_ellipsis_args":false,"name":"_prepare_rebalance of UsersDispatcher","ret_type":{".class":"NoneType"},"type_guard":null,"type_is":null,"unpack_kwargs":false,"variables":[]}}},"_rebalance":{".class":"SymbolTableNode","implicit":true,"kind":"Mdef","node":{".class":"Var","flags":["is_ready","is_inferred"],"fullname":"locust.dispatch.UsersDispatcher._rebalance","name":"_rebalance","setter_type":null,"type":"builtins.bool"}},"_remove_users_from_workers":{".class":"SymbolTableNode","kind":"Mdef","node":{".class":"FuncDef","abstract_status":0,"arg_kinds":[0],"arg_names":["self"],"dataclass_transform_spec":null,"deprecated":null,"flags":["is_trivial_self"],"fullname":"locust.dispatch.UsersDispatcher._remove_users_from_workers","name":"_remove_users_from_workers","original_first_arg":"self","type":{".class":"CallableType","arg_kinds":[0],"arg_names":["self"],"arg_types":["locust.dispatch.UsersDispatcher"],"fallback":"builtins.function","from_concatenate":false,"implicit":false,"imprecise_arg_kinds":false,"is_bound":false,"is_ellipsis_args":false,"name":"_remove_users_from_workers of UsersDispatcher","ret_type":{".class":"Instance","args":["builtins.str",{".class":"Instance","args":["builtins.str","builtins.int"],"extra_attrs":null,"type_ref":"builtins.dict"}],"extra_attrs":null,"type_ref":"builtins.dict"},"type_guard":null,"type_is":null,"unpack_kwargs":false,"variables":[]}}},"_sort_workers":{".class":"SymbolTableNode","kind":"Mdef","node":{".class":"FuncDef","abstract_status":0,"arg_kinds":[0],"arg_names":["self"],"dataclass_transform_spec":null,"deprecated":null,"flags":[],"fullname":"locust.dispatch.UsersDispatcher._sort_workers","name":"_sort_workers","original_first_arg":"self","type":null}},"_spawn_rate":{".class":"SymbolTableNode","implicit":true,"kind":"Mdef","node":{".class":"Var","flags":["explicit_self_type","is_ready","is_inferred"],"fullname":"locust.dispatch.UsersDispatcher._spawn_rate","name":"_spawn_rate","setter_type":null,"type":"builtins.float"}},"_target_user_count":{".class":"SymbolTableNode","implicit":true,"kind":"Mdef","node":{".class":"Var","flags":["explicit_self_type","is_ready","is_inferred"],"fullname":"locust.dispatch.UsersDispatcher._target_user_count","name":"_target_user_count","setter_type":null,"type":"builtins.int"}},"_try_dispatch_fixed":{".class":"SymbolTableNode","implicit":true,"kind":"Mdef","node":{".class":"Var","flags":["is_ready","is_inferred"],"fullname":"locust.dispatch.UsersDispatcher._try_dispatch_fixed","name":"_try_dispatch_fixed","setter_type":null,"type":"builtins.bool"}},"_user_classes":{".class":"SymbolTableNode","implicit":true,"kind":"Mdef","node":{".class":"Var","flags":["is_ready","is_inferred"],"fullname":"locust.dispatch.UsersDispatcher._user_classes","name":"_user_classes","setter_type":null,"type":{".class":"Instance","args":[{".class":"TypeType","is_type_form":false,"item":"locust.user.users.User"}],"extra_attrs":null,"type_ref":"builtins.list"}}},"_user_count_per_dispatch_iteration":{".class":"SymbolTableNode","implicit":true,"kind":"Mdef","node":{".class":"Var","flags":["explicit_self_type","is_ready","is_inferred"],"fullname":"locust.dispatch.UsersDispatcher._user_count_per_dispatch_iteration","name":"_user_count_per_dispatch_iteration","setter_type":null,"type":"builtins.int"}},"_user_gen":{".class":"SymbolTableNode","kind":"Mdef","node":{".class":"FuncDef","abstract_status":0,"arg_kinds":[0],"arg_names":["self"],"dataclass_transform_spec":null,"deprecated":null,"flags":["is_generator","is_trivial_self"],"fullname":"locust.dispatch.UsersDispatcher._user_gen","name":"_user_gen","original_first_arg":"self","type":{".class":"CallableType","arg_kinds":[0],"arg_names":["self"],"arg_types":["locust.dispatch.UsersDispatcher"],"fallback":"builtins.function","from_concatenate":false,"implicit":false,"imprecise_arg_kinds":false,"is_bound":false,"is_ellipsis_args":false,"name":"_user_gen of UsersDispatcher","ret_type":{".class":"Instance","args":[{".class":"UnionType","items":["builtins.str",{".class":"NoneType"}],"uses_pep604_syntax":true}],"extra_attrs":null,"type_ref":"typing.Iterator"},"type_guard":null,"type_is":null,"unpack_kwargs":false,"variables":[]}}},"_user_generator":{".class":"SymbolTableNode","implicit":true,"kind":"Mdef","node":{".class":"Var","flags":["is_ready","is_inferred"],"fullname":"locust.dispatch.UsersDispatcher._user_generator","name":"_user_generator","setter_type":null,"type":{".class":"Instance","args":[{".class":"UnionType","items":["builtins.str",{".class":"NoneType"}],"uses_pep604_syntax":true}],"extra_attrs":null,"type_ref":"typing.Iterator"}}},"_users_on_workers":{".class":"SymbolTableNode","implicit":true,"kind":"Mdef","node":{".class":"Var","flags":["is_ready","is_inferred"],"fullname":"locust.dispatch.UsersDispatcher._users_on_workers","name":"_users_on_workers","setter_type":null,"type":{".class":"Instance","args":["builtins.str",{".class":"Instance","args":["builtins.str","builtins.int"],"extra_attrs":null,"type_ref":"builtins.dict"}],"extra_attrs":null,"type_ref":"builtins.dict"}}},"_wait_between_dispatch":{".class":"SymbolTableNode","implicit":true,"kind":"Mdef","node":{".class":"Var","flags":["explicit_self_type","is_ready","is_inferred"],"fullname":"locust.dispatch.UsersDispatcher._wait_between_dispatch","name":"_wait_between_dispatch","setter_type":null,"type":"builtins.float"}},"_wait_between_dispatch_iteration_context":{".class":"SymbolTableNode","kind":"Mdef","node":{".class":"Decorator","func":{".class":"FuncDef","abstract_status":0,"arg_kinds":[0],"arg_names":["self"],"dataclass_transform_spec":null,"deprecated":null,"flags":["is_decorated","is_trivial_self"],"fullname":"locust.dispatch.UsersDispatcher._wait_between_dispatch_iteration_context","name":"_wait_between_dispatch_iteration_context","original_first_arg":"self","type":{".class":"CallableType","arg_kinds":[0],"arg_names":["self"],"arg_types":["locust.dispatch.UsersDispatcher"],"fallback":"builtins.function","from_concatenate":false,"implicit":false,"imprecise_arg_kinds":false,"is_bound":false,"is_ellipsis_args":false,"name":"_wait_between_dispatch_iteration_context of UsersDispatcher","ret_type":{".class":"Instance","args":[{".class":"NoneType"},{".class":"NoneType"},{".class":"NoneType"}],"extra_attrs":null,"type_ref":"typing.Generator"},"type_guard":null,"type_is":null,"unpack_kwargs":false,"variables":[]}},"is_overload":false,"var":{".class":"Var","flags":["is_initialized_in_class","is_ready","is_inferred"],"fullname":"locust.dispatch.UsersDispatcher._wait_between_dispatch_iteration_context","name":"_wait_between_dispatch_iteration_context","setter_type":null,"type":{".class":"CallableType","arg_kinds":[0],"arg_names":["self"],"arg_types":["locust.dispatch.UsersDispatcher"],"fallback":"builtins.function","from_concatenate":false,"implicit":false,"imprecise_arg_kinds":false,"is_bound":false,"is_ellipsis_args":false,"name":"_wait_between_dispatch_iteration_context of UsersDispatcher","ret_type":{".class":"Instance","args":[{".class":"NoneType"},{".class":"NoneType"},{".class":"NoneType"}],"extra_attrs":null,"type_ref":"contextlib._GeneratorContextManager"},"type_guard":null,"type_is":null,"unpack_kwargs":false,"variables":[]}}}},"_worker_node_generator":{".class":"SymbolTableNode","implicit":true,"kind":"Mdef","node":{".class":"Var","flags":["is_ready","is_inferred"],"fullname":"locust.dispatch.UsersDispatcher._worker_node_generator","name":"_worker_node_generator","setter_type":null,"type":{".class":"Instance","args":["locust.runners.WorkerNode"],"extra_attrs":null,"type_ref":"itertools.cycle"}}},"_worker_nodes":{".class":"SymbolTableNode","implicit":true,"kind":"Mdef","node":{".class":"Var","flags":["is_ready","is_inferred"],"fullname":"locust.dispatch.UsersDispatcher._worker_nodes","name":"_worker_nodes","setter_type":null,"type":{".class":"Instance","args":["locust.runners.WorkerNode"],"extra_attrs":null,"type_ref":"builtins.list"}}},"add_worker":{".class":"SymbolTableNode","kind":"Mdef","node":{".class":"FuncDef","abstract_status":0,"arg_kinds":[0,0],"arg_names":["self","worker_node"],"dataclass_transform_spec":null,"deprecated":null,"flags":["is_trivial_self"],"fullname":"locust.dispatch.UsersDispatcher.add_worker","name":"add_worker","original_first_arg":"self","type":{".class":"CallableType","arg_kinds":[0,0],"arg_names":["self","worker_node"],"arg_types":["locust.dispatch.UsersDispatcher","locust.runners.WorkerNode"],"fallback":"builtins.function","from_concatenate":false,"implicit":false,"imprecise_arg_kinds":false,"is_bound":false,"is_ellipsis_args":false,"name":"add_worker of UsersDispatcher","ret_type":{".class":"NoneType"},"type_guard":null,"type_is":null,"unpack_kwargs":false,"variables":[]}}},"dispatch_in_progress":{".class":"SymbolTableNode","kind":"Mdef","node":{".class":"Decorator","func":{".class":"FuncDef","abstract_status":0,"arg_kinds":[0],"arg_names":["self"],"dataclass_transform_spec":null,"deprecated":null,"flags":["is_property","is_decorated","is_trivial_self"],"fullname":"locust.dispatch.UsersDispatcher.dispatch_in_progress","name":"dispatch_in_progress","original_first_arg":"self","type":{".class":"CallableType","arg_kinds":[0],"arg_names":["self"],"arg_types":["locust.dispatch.UsersDispatcher"],"fallback":"builtins.function","from_concatenate":false,"implicit":false,"imprecise_arg_kinds":false,"is_bound":false,"is_ellipsis_args":false,"name":"dispatch_in_progress of UsersDispatcher","ret_type":"builtins.bool","type_guard":null,"type_is":null,"unpack_kwargs":false,"variables":[]}},"is_overload":false,"var":{".class":"Var","flags":["is_initialized_in_class","is_property","is_ready","is_inferred"],"fullname":"locust.dispatch.UsersDispatcher.dispatch_in_progress","name":"dispatch_in_progress","setter_type":null,"type":{".class":"CallableType","arg_kinds":[0],"arg_names":["self"],"arg_types":["locust.dispatch.UsersDispatcher"],"fallback":"builtins.function","from_concatenate":false,"implicit":false,"imprecise_arg_kinds":false,"is_bound":false,"is_ellipsis_args":false,"name":"dispatch_in_progress of UsersDispatcher","ret_type":"builtins.bool","type_guard":null,"type_is":null,"unpack_kwargs":false,"variables":[]}}}},"dispatch_iteration_durations":{".class":"SymbolTableNode","kind":"Mdef","node":{".class":"Decorator","func":{".class":"FuncDef","abstract_status":0,"arg_kinds":[0],"arg_names":["self"],"dataclass_transform_spec":null,"deprecated":null,"flags":["is_property","is_decorated","is_trivial_self"],"fullname":"locust.dispatch.UsersDispatcher.dispatch_iteration_durations","name":"dispatch_iteration_durations","original_first_arg":"self","type":{".class":"CallableType","arg_kinds":[0],"arg_names":["self"],"arg_types":["locust.dispatch.UsersDispatcher"],"fallback":"builtins.function","from_concatenate":false,"implicit":false,"imprecise_arg_kinds":false,"is_bound":false,"is_ellipsis_args":false,"name":"dispatch_iteration_durations of UsersDispatcher","ret_type":{".class":"Instance","args":["builtins.float"],"extra_attrs":null,"type_ref":"builtins.list"},"type_guard":null,"type_is":null,"unpack_kwargs":false,"variables":[]}},"is_overload":false,"var":{".class":"Var","flags":["is_initialized_in_class","is_property","is_ready","is_inferred"],"fullname":"locust.dispatch.UsersDispatcher.dispatch_iteration_durations","name":"dispatch_iteration_durations","setter_type":null,"type":{".class":"CallableType","arg_kinds":[0],"arg_names":["self"],"arg_types":["locust.dispatch.UsersDispatcher"],"fallback":"builtins.function","from_concatenate":false,"implicit":false,"imprecise_arg_kinds":false,"is_bound":false,"is_ellipsis_args":false,"name":"dispatch_iteration_durations of UsersDispatcher","ret_type":{".class":"Instance","args":["builtins.float"],"extra_attrs":null,"type_ref":"builtins.list"},"type_guard":null,"type_is":null,"unpack_kwargs":false,"variables":[]}}}},"get_current_user_count":{".class":"SymbolTableNode","kind":"Mdef","node":{".class":"FuncDef","abstract_status":0,"arg_kinds":[0],"arg_names":["self"],"dataclass_transform_spec":null,"deprecated":null,"flags":["is_trivial_self"],"fullname":"locust.dispatch.UsersDispatcher.get_current_user_count","name":"get_current_user_count","original_first_arg":"self","type":{".class":"CallableType","arg_kinds":[0],"arg_names":["self"],"arg_types":["locust.dispatch.UsersDispatcher"],"fallback":"builtins.function","from_concatenate":false,"implicit":false,"imprecise_arg_kinds":false,"is_bound":false,"is_ellipsis_args":false,"name":"get_current_user_count of UsersDispatcher","ret_type":"builtins.int","type_guard":null,"type_is":null,"unpack_kwargs":false,"variables":[]}}},"new_dispatch":{".class":"SymbolTableNode","kind":"Mdef","node":{".class":"FuncDef","abstract_status":0,"arg_kinds":[0,0,0,1],"arg_names":["self","target_user_count","spawn_rate","user_classes"],"dataclass_transform_spec":null,"deprecated":null,"flags":["is_trivial_self"],"fullname":"locust.dispatch.UsersDispatcher.new_dispatch","name":"new_dispatch","original_first_arg":"self","type":{".class":"CallableType","arg_kinds":[0,0,0,1],"arg_names":["self","target_user_count","spawn_rate","user_classes"],"arg_types":["locust.dispatch.UsersDispatcher","builtins.int","builtins.float",{".class":"UnionType","items":[{".class":"Instance","args":[{".class":"TypeType","is_type_form":false,"item":"locust.user.users.User"}],"extra_attrs":null,"type_ref":"builtins.list"},{".class":"NoneType"}],"uses_pep604_syntax":true}],"fallback":"builtins.function","from_concatenate":false,"implicit":false,"imprecise_arg_kinds":false,"is_bound":false,"is_ellipsis_args":false,"name":"new_dispatch of UsersDispatcher","ret_type":{".class":"NoneType"},"type_guard":null,"type_is":null,"unpack_kwargs":false,"variables":[]}}},"remove_worker":{".class":"SymbolTableNode","kind":"Mdef","node":{".class":"FuncDef","abstract_status":0,"arg_kinds":[0,0],"arg_names":["self","worker_node"],"dataclass_transform_spec":null,"deprecated":null,"flags":["is_trivial_self"],"fullname":"locust.dispatch.UsersDispatcher.remove_worker","name":"remove_worker","original_first_arg":"self","type":{".class":"CallableType","arg_kinds":[0,0],"arg_names":["self","worker_node"],"arg_types":["locust.dispatch.UsersDispatcher","locust.runners.WorkerNode"],"fallback":"builtins.function","from_concatenate":false,"implicit":false,"imprecise_arg_kinds":false,"is_bound":false,"is_ellipsis_args":false,"name":"remove_worker of UsersDispatcher","ret_type":{".class":"NoneType"},"type_guard":null,"type_is":null,"unpack_kwargs":false,"variables":[]}}}},"self_type":{".class":"TypeVarType","default":{".class":"AnyType","missing_import_name":null,"source_any":null,"type_of_any":4},"fullname":"locust.dispatch.UsersDispatcher.Self","id":0,"name":"Self","namespace":"","upper_bound":"locust.dispatch.UsersDispatcher","values":[],"variance":0},"slots":null,"tuple_type":null,"type_vars":[],"typeddict_type":null}},"WorkerNode":{".class":"SymbolTableNode","cross_ref":"locust.runners.WorkerNode","kind":"Gdef"},"__annotations__":{".class":"SymbolTableNode","kind":"Gdef","node":{".class":"Var","flags":["is_ready"],"fullname":"locust.dispatch.__annotations__","name":"__annotations__","setter_type":null,"type":{".class":"Instance","args":["builtins.str",{".class":"AnyType","missing_import_name":null,"source_any":null,"type_of_any":6}],"extra_attrs":null,"type_ref":"builtins.dict"}}},"__doc__":{".class":"SymbolTableNode","kind":"Gdef","node":{".class":"Var","flags":["is_ready"],"fullname":"locust.dispatch.__doc__","name":"__doc__","setter_type":null,"type":"builtins.str"}},"__file__":{".class":"SymbolTableNode","kind":"Gdef","node":{".class":"Var","flags":["is_ready"],"fullname":"locust.dispatch.__file__","name":"__file__","setter_type":null,"type":"builtins.str"}},"__name__":{".class":"SymbolTableNode","kind":"Gdef","node":{".class":"Var","flags":["is_ready"],"fullname":"locust.dispatch.__name__","name":"__name__","setter_type":null,"type":"builtins.str"}},"__package__":{".class":"SymbolTableNode","kind":"Gdef","node":{".class":"Var","flags":["is_ready"],"fullname":"locust.dispatch.__package__","name":"__package__","setter_type":null,"type":"builtins.str"}},"__spec__":{".class":"SymbolTableNode","kind":"Gdef","node":{".class":"Var","flags":["is_ready"],"fullname":"locust.dispatch.__spec__","name":"__spec__","setter_type":null,"type":"_frozen_importlib.ModuleSpec"}},"_kl_generator":{".class":"SymbolTableNode","kind":"Gdef","node":{".class":"FuncDef","abstract_status":0,"arg_kinds":[0],"arg_names":["users"],"dataclass_transform_spec":null,"deprecated":null,"flags":[],"fullname":"locust.dispatch._kl_generator","name":"_kl_generator","original_first_arg":"users","type":{".class":"CallableType","arg_kinds":[0],"arg_names":["users"],"arg_types":[{".class":"Instance","args":[{".class":"TupleType","implicit":false,"items":[{".class":"TypeVarType","default":{".class":"AnyType","missing_import_name":null,"source_any":null,"type_of_any":4},"fullname":"locust.dispatch.T","id":-1,"name":"T","namespace":"locust.dispatch._kl_generator","upper_bound":"builtins.object","values":[],"variance":0},"builtins.float"],"partial_fallback":{".class":"Instance","args":[{".class":"AnyType","missing_import_name":null,"source_any":null,"type_of_any":6}],"extra_attrs":null,"type_ref":"builtins.tuple"}}],"extra_attrs":null,"type_ref":"typing.Iterable"}],"fallback":"builtins.function","from_concatenate":false,"implicit":false,"imprecise_arg_kinds":false,"is_bound":false,"is_ellipsis_args":false,"name":"_kl_generator","ret_type":{".class":"Instance","args":[{".class":"UnionType","items":[{".class":"TypeVarType","default":{".class":"AnyType","missing_import_name":null,"source_any":null,"type_of_any":4},"fullname":"locust.dispatch.T","id":-1,"name":"T","namespace":"locust.dispatch._kl_generator","upper_bound":"builtins.object","values":[],"variance":0},{".class":"NoneType"}],"uses_pep604_syntax":false},{".class":"NoneType"},{".class":"NoneType"}],"extra_attrs":null,"type_ref":"typing.Generator"},"type_guard":null,"type_is":null,"unpack_kwargs":false,"variables":[{".class":"TypeVarType","default":{".class":"AnyType","missing_import_name":null,"source_any":null,"type_of_any":4},"fullname":"locust.dispatch.T","id":-1,"name":"T","namespace":"locust.dispatch._kl_generator","upper_bound":"builtins.object","values":[],"variance":0}]}}},"annotations":{".class":"SymbolTableNode","cross_ref":"__future__.annotations","kind":"Gdef"},"attrgetter":{".class":"SymbolTableNode","cross_ref":"operator.attrgetter","kind":"Gdef"},"contextlib":{".class":"SymbolTableNode","cross_ref":"contextlib","kind":"Gdef"},"defaultdict":{".class":"SymbolTableNode","cross_ref":"collections.defaultdict","kind":"Gdef"},"gevent":{".class":"SymbolTableNode","kind":"Gdef","node":{".class":"Var","flags":["is_suppressed_import","is_ready","is_inferred"],"fullname":"locust.dispatch.gevent","name":"gevent","setter_type":null,"type":{".class":"AnyType","missing_import_name":"locust.dispatch.gevent","source_any":null,"type_of_any":3}}},"heapify":{".class":"SymbolTableNode","cross_ref":"_heapq.heapify","kind":"Gdef"},"heapreplace":{".class":"SymbolTableNode","cross_ref":"_heapq.heapreplace","kind":"Gdef"},"itertools":{".class":"SymbolTableNode","cross_ref":"itertools","kind":"Gdef"},"log2":{".class":"SymbolTableNode","cross_ref":"math.log2","kind":"Gdef"},"math":{".class":"SymbolTableNode","cross_ref":"math","kind":"Gdef"},"time":{".class":"SymbolTableNode","cross_ref":"time","kind":"Gdef"}},"path":"/Users/noufi1/Library/Python/3.9/lib/python/site-packages/locust/dispatch.py"}